sbt_aws_cli_testt/__init__.py
sbt_aws_cli_testt/__main__.py
sbt_aws_cli_testt/main.py
sbt_aws_cli_testt-0.1.4.dist-info/METADATA
sbt_aws_cli_testt-0.1.4.dist-info/WHEEL
sbt_aws_cli_testt-0.1.4.dist-info/entry_points.txt
sbt_aws_cli_testt-0.1.4.dist-info/RECORD
